ezpyzy/__init__.py
ezpyzy/allargs.py
ezpyzy/argcast.py
ezpyzy/autocache.py
ezpyzy/batch.py
ezpyzy/bind.py
ezpyzy/captured_vars.py
ezpyzy/check.py
ezpyzy/denominate.py
ezpyzy/digital_iteration.py
ezpyzy/expydite.py
ezpyzy/file.py
ezpyzy/fixture_group.py
ezpyzy/format.py
ezpyzy/option.py
ezpyzy/printer.py
ezpyzy/scratch.py
ezpyzy/send_email.py
ezpyzy/settings.py
ezpyzy/short_uuid.py
ezpyzy/shush.py
ezpyzy/singleton.py
ezpyzy/subproc.py
ezpyzy/table.py
ezpyzy/timer.py
ezpyzy-0.2.0.dist-info/METADATA
ezpyzy-0.2.0.dist-info/WHEEL
ezpyzy-0.2.0.dist-info/RECORD
